embedded_topic_model/__init__.py
embedded_topic_model/models/__init__.py
embedded_topic_model/models/etm.py
embedded_topic_model/models/model.py
embedded_topic_model/utils/__init__.py
embedded_topic_model/utils/data.py
embedded_topic_model/utils/embedding.py
embedded_topic_model/utils/metrics.py
embedded_topic_model/utils/preprocessing.py
embedded_topic_model-1.2.1.dist-info/LICENSE
embedded_topic_model-1.2.1.dist-info/METADATA
embedded_topic_model-1.2.1.dist-info/WHEEL
embedded_topic_model-1.2.1.dist-info/top_level.txt
embedded_topic_model-1.2.1.dist-info/RECORD
