Metadata-Version: 2.1
Name: embedded-topic-model
Version: 1.2.1
Summary: A package to run embedded topic modelling
Home-page: https://github.com/lffloyd/embedded-topic-model
Author: Luiz F. Matos
Author-email: lfmatosmelo@id.uff.br
License: MIT license
Keywords: embedded_topic_model
Classifier: Intended Audience :: Science/Research
Classifier: Intended Audience :: Developers
Classifier: License :: OSI Approved :: MIT License
Classifier: Natural Language :: English
Classifier: Programming Language :: Python
Classifier: Programming Language :: Python :: 3.9
Classifier: Programming Language :: Python :: 3.10
Classifier: Programming Language :: Python :: 3.11
Classifier: Topic :: Software Development
Classifier: Topic :: Scientific/Engineering
Classifier: Topic :: Scientific/Engineering :: Artificial Intelligence
Classifier: Operating System :: MacOS
Classifier: Operating System :: Unix
Requires-Python: >=3.9
License-File: LICENSE
Requires-Dist: gensim >=4.3
Requires-Dist: nltk >=3.8
Requires-Dist: numpy >=1.25
Requires-Dist: scikit-learn >=1.3
Requires-Dist: scipy >=1.11
Requires-Dist: torch >=2.0
